{"type":"object","additionalProperties":false,"required":["requested_mode","count","hits"],"properties":{"requested_mode":{"type":"string","enum":["semantic","direct"]},"count":{"type":"integer","minimum":0},"hits":{"type":"array","items":{"type":"object","additionalProperties":false,"required":["score","snippet","origin","metadata"],"properties":{"score":{"type":"number"},"snippet":{"type":"string"},"origin":{"type":"string"},"metadata":{"type":"object","additionalProperties":false,"required":["title","relative_path","uuid","area","type","tags","date","updated","source","source_type","file_type"],"properties":{"title":{"type":"string"},"relative_path":{"type":"string"},"uuid":{"type":"string"},"area":{"type":"string"},"type":{"type":"string"},"tags":{"type":"array","items":{"type":"string"}},"date":{"type":"string"},"updated":{"type":"string"},"source":{"type":"array","items":{"type":"string"}},"source_type":{"type":"string"},"file_type":{"type":"string"}}}}}}}}
